DashArray/__init__.py
dasharray-0.0.1.dist-info/LICENSE
dasharray-0.0.1.dist-info/METADATA
dasharray-0.0.1.dist-info/WHEEL
dasharray-0.0.1.dist-info/top_level.txt
dasharray-0.0.1.dist-info/RECORD
