Metadata-Version: 2.1
Name: dasharray
Version: 0.0.1
Summary: A small addition to the python list type to include a safe get
Home-page: https://github.com/danecwalker/Dash-Array
Author: Dane Walker
Author-email: dane@danecwalker.com
License: UNKNOWN
Project-URL: Bug Tracker, https://github.com/danecwalker/Dash-Array/issues
Platform: UNKNOWN
Classifier: Programming Language :: Python :: 3
Classifier: License :: OSI Approved :: MIT License
Classifier: Operating System :: OS Independent
Requires-Python: >=3.6
License-File: LICENSE
